fair_identifiers_client/__init__.py
fair_identifiers_client/config.py
fair_identifiers_client/helpers.py
fair_identifiers_client/identifiers_api.py
fair_identifiers_client/local_server.py
fair_identifiers_client/login.py
fair_identifiers_client/main.py
fair_identifiers_client/__pycache__/__init__.cpython-38.pyc
fair_identifiers_client/__pycache__/config.cpython-38.pyc
fair_identifiers_client/__pycache__/helpers.cpython-38.pyc
fair_identifiers_client/__pycache__/identifiers_api.cpython-38.pyc
fair_identifiers_client/__pycache__/local_server.cpython-38.pyc
fair_identifiers_client/__pycache__/login.cpython-38.pyc
fair_identifiers_client/__pycache__/main.cpython-38.pyc
fair_identifiers_client-0.5.1.dist-info/LICENSE
fair_identifiers_client-0.5.1.dist-info/METADATA
fair_identifiers_client-0.5.1.dist-info/WHEEL
fair_identifiers_client-0.5.1.dist-info/entry_points.txt
fair_identifiers_client-0.5.1.dist-info/top_level.txt
fair_identifiers_client-0.5.1.dist-info/RECORD
