Metadata-Version: 2.1
Name: fair-identifiers-client
Version: 0.5.1
Summary: FAIR Research Identifiers Service Client
Home-page: https://github.com/fair-research/fair-identifiers-client
Author: FAIR Research Team
License: Apache 2.0
Classifier: Intended Audience :: Developers
Classifier: Intended Audience :: Science/Research
Classifier: License :: OSI Approved :: Apache Software License
Classifier: Programming Language :: Python :: 3.6
Classifier: Programming Language :: Python :: 3.7
Classifier: Programming Language :: Python :: 3.8
Classifier: Operating System :: POSIX
License-File: LICENSE
Requires-Dist: globus-sdk <4.0.0,>=1.6.0
Requires-Dist: six <2.0.0,>=1.10.0
